cfnStack/__init__.py
cfnStack/default_stack.yaml.jinja
cfnStack/determine_actions.py
cfnStack/stack.py
cfn_ci_helper-2023.10.16.post0.data/scripts/deploy_cf.py
cfn_ci_helper-2023.10.16.post0.dist-info/licenses/LICENSE
cfn_ci_helper-2023.10.16.post0.dist-info/METADATA
cfn_ci_helper-2023.10.16.post0.dist-info/WHEEL
cfn_ci_helper-2023.10.16.post0.dist-info/top_level.txt
cfn_ci_helper-2023.10.16.post0.dist-info/RECORD
