Metadata-Version: 2.4
Name: cfn-ci-helper
Version: 2023.10.16.post0
Summary: A Cloudformation CI Helper System
Home-page: https://github.com/chalbersma/cfn-ci-helper
Author: Chris Halbersma
Author-email: chris@halbersma.us
Classifier: Programming Language :: Python :: 3
Classifier: Operating System :: OS Independent
Requires-Python: >=3.8
License-File: LICENSE
Requires-Dist: jinja2>=3.0.2
Requires-Dist: texttable
Dynamic: license-file
